{
    "name": "topcoat",
    "version": "0.1.0",
    "main": [
        "release/css/topcoat-min.css",
        "release/css/topcoat.css",
        "release/font/font",
        "release/font/LICENSE.txt",
        "release/font/SourceCodePro",
        "release/font/SourceCodePro-Black.otf",
        "release/font/SourceCodePro-Bold.otf",
        "release/font/SourceCodePro-ExtraLight.otf",
        "release/font/SourceCodePro-Light.otf",
        "release/font/SourceCodePro-Regular.otf",
        "release/font/SourceCodePro-Semibold.otf",
        "release/font/SourceSansPro",
        "release/font/SourceSansPro-Black.otf",
        "release/font/SourceSansPro-BlackIt.otf",
        "release/font/SourceSansPro-Bold.otf",
        "release/font/SourceSansPro-BoldIt.otf",
        "release/font/SourceSansPro-ExtraLight.otf",
        "release/font/SourceSansPro-ExtraLightIt.otf",
        "release/font/SourceSansPro-It.otf",
        "release/font/SourceSansPro-Light.otf",
        "release/font/SourceSansPro-LightIt.otf",
        "release/font/SourceSansPro-Regular.otf",
        "release/font/SourceSansPro-Semibold.otf",
        "release/font/SourceSansPro-SemiboldIt.otf",
        "release/img/bg_dark.png",
        "release/img/breadcrumb.png",
        "release/img/checkbox_checked.png",
        "release/img/checkbox_checked_dark.png",
        "release/img/checkbox_unchecked.png",
        "release/img/checkbox_unchecked_dark.png",
        "release/img/dark-grips.png",
        "release/img/dark-sprites.png",
        "release/img/dark-sprites2x.png",
        "release/img/dialog-zone-bg.png",
        "release/img/drop-down-triangle-dark.png",
        "release/img/drop-down-triangle.png",
        "release/img/img",
        "release/img/light-grips.png",
        "release/img/light-sprites.png",
        "release/img/light-sprites2x.png",
        "release/img/pop-up-triangle-dark.png",
        "release/img/pop-up-triangle.png",
        "release/img/search-bg.png",
        "release/img/search-bg2x.png",
        "release/img/spinner-lrg.png",
        "release/img/spinner-lrg@2x.png",
        "release/img/spinner-sml.png",
        "release/img/spinner.png"
    ],
    "repo": "topcoat/topcoat",
    "description": "An experimental CSS library.",
    "styles": [
        "release/css/topcoat-min.css"
    ],
    "files": [
        "release/font/font",
        "release/font/LICENSE.txt",
        "release/font/SourceCodePro",
        "release/font/SourceCodePro-Black.otf",
        "release/font/SourceCodePro-Bold.otf",
        "release/font/SourceCodePro-ExtraLight.otf",
        "release/font/SourceCodePro-Light.otf",
        "release/font/SourceCodePro-Regular.otf",
        "release/font/SourceCodePro-Semibold.otf",
        "release/font/SourceSansPro",
        "release/font/SourceSansPro-Black.otf",
        "release/font/SourceSansPro-BlackIt.otf",
        "release/font/SourceSansPro-Bold.otf",
        "release/font/SourceSansPro-BoldIt.otf",
        "release/font/SourceSansPro-ExtraLight.otf",
        "release/font/SourceSansPro-ExtraLightIt.otf",
        "release/font/SourceSansPro-It.otf",
        "release/font/SourceSansPro-Light.otf",
        "release/font/SourceSansPro-LightIt.otf",
        "release/font/SourceSansPro-Regular.otf",
        "release/font/SourceSansPro-Semibold.otf",
        "release/font/SourceSansPro-SemiboldIt.otf",
        "release/img/bg_dark.png",
        "release/img/breadcrumb.png",
        "release/img/checkbox_checked.png",
        "release/img/checkbox_checked_dark.png",
        "release/img/checkbox_unchecked.png",
        "release/img/checkbox_unchecked_dark.png",
        "release/img/dark-grips.png",
        "release/img/dark-sprites.png",
        "release/img/dark-sprites2x.png",
        "release/img/dialog-zone-bg.png",
        "release/img/drop-down-triangle-dark.png",
        "release/img/drop-down-triangle.png",
        "release/img/img",
        "release/img/light-grips.png",
        "release/img/light-sprites.png",
        "release/img/light-sprites2x.png",
        "release/img/pop-up-triangle-dark.png",
        "release/img/pop-up-triangle.png",
        "release/img/search-bg.png",
        "release/img/search-bg2x.png",
        "release/img/spinner-lrg.png",
        "release/img/spinner-lrg@2x.png",
        "release/img/spinner-sml.png",
        "release/img/spinner.png"
    ]
}